opencollective/__init__.py
opencollective/auth.py
opencollective/cli.py
opencollective/client.py
opencollective/mcp_server.py
opencollective-0.2.1.dist-info/METADATA
opencollective-0.2.1.dist-info/WHEEL
opencollective-0.2.1.dist-info/entry_points.txt
opencollective-0.2.1.dist-info/licenses/LICENSE
opencollective-0.2.1.dist-info/RECORD
