Metadata-Version: 2.4
Name: opencollective
Version: 0.2.1
Summary: Unofficial Python client for the OpenCollective GraphQL API
Project-URL: Homepage, https://github.com/MaxGhenis/opencollective-py
Project-URL: Documentation, https://maxghenis.github.io/opencollective-py
Author-email: Max Ghenis <max@maxghenis.com>
License-Expression: MIT
License-File: LICENSE
Classifier: Development Status :: 3 - Alpha
Classifier: Intended Audience :: Developers
Classifier: License :: OSI Approved :: MIT License
Classifier: Programming Language :: Python :: 3
Classifier: Programming Language :: Python :: 3.10
Classifier: Programming Language :: Python :: 3.11
Classifier: Programming Language :: Python :: 3.12
Classifier: Programming Language :: Python :: 3.13
Requires-Python: >=3.10
Requires-Dist: click>=8.0
Requires-Dist: requests>=2.28
Provides-Extra: all
Requires-Dist: black>=23.0; extra == 'all'
Requires-Dist: mcp>=1.0; extra == 'all'
Requires-Dist: mypy>=1.0; extra == 'all'
Requires-Dist: myst-parser>=2.0; extra == 'all'
Requires-Dist: pytest-cov>=4.0; extra == 'all'
Requires-Dist: pytest>=7.0; extra == 'all'
Requires-Dist: responses>=0.23; extra == 'all'
Requires-Dist: ruff>=0.1; extra == 'all'
Requires-Dist: sphinx>=7.0; extra == 'all'
Requires-Dist: weasyprint>=60.0; extra == 'all'
Provides-Extra: dev
Requires-Dist: black>=23.0; extra == 'dev'
Requires-Dist: mcp>=1.0; extra == 'dev'
Requires-Dist: mypy>=1.0; extra == 'dev'
Requires-Dist: pytest-cov>=4.0; extra == 'dev'
Requires-Dist: pytest>=7.0; extra == 'dev'
Requires-Dist: responses>=0.23; extra == 'dev'
Requires-Dist: ruff>=0.1; extra == 'dev'
Requires-Dist: weasyprint>=60.0; extra == 'dev'
Provides-Extra: docs
Requires-Dist: myst-parser>=2.0; extra == 'docs'
Requires-Dist: sphinx>=7.0; extra == 'docs'
Provides-Extra: mcp
Requires-Dist: mcp>=1.0; extra == 'mcp'
Provides-Extra: pdf
Requires-Dist: weasyprint>=60.0; extra == 'pdf'
